<class>com.egen.develop.integration.model.VObject</class>
<lastUsedTemplate>e-gen_jdbcutil_standard_entity_mapping</lastUsedTemplate>
<componentType>com.egen.webide.integration.components.StandardJavaview</componentType>
<name>Jw_abastecimento_materiais_fornec</name>
<columns>
<columns_item>
<class>com.egen.develop.integration.model.VObjectColumn</class>
<discard>false</discard>
<columnName>fornecedor_codigo</columnName>
<columnProperties>
<columnProperties_item>
<$key>not_null</$key>
<$value></$value>
</columnProperties_item>
<columnProperties_item>
<$key>help</$key>
<$value></$value>
</columnProperties_item>
<columnProperties_item>
<$key>case_restriction</$key>
<$value></$value>
</columnProperties_item>
<columnProperties_item>
<$key>validate_type</$key>
<$value></$value>
</columnProperties_item>
<columnProperties_item>
<$key>length</$key>
<$value>-105</$value>
</columnProperties_item>
<columnProperties_item>
<$key>html_type</$key>
<$value>text</$value>
</columnProperties_item>
<columnProperties_item>
<$key>i18n</$key>
<$value></$value>
</columnProperties_item>
<columnProperties_item>
<$key>label</$key>
<$value>fornecedor_codigo</$value>
</columnProperties_item>
<columnProperties_item>
<$key>format</$key>
<$value></$value>
</columnProperties_item>
<columnProperties_item>
<$key>type</$key>
<$value>java.lang.Long</$value>
</columnProperties_item>
<columnProperties_item>
<$key>size</$key>
<$value>22</$value>
</columnProperties_item>
</columnProperties>
</columns_item>
<columns_item>
<class>com.egen.develop.integration.model.VObjectColumn</class>
<discard>false</discard>
<columnName>fen_seq</columnName>
<columnProperties>
<columnProperties_item>
<$key>not_null</$key>
<$value></$value>
</columnProperties_item>
<columnProperties_item>
<$key>help</$key>
<$value></$value>
</columnProperties_item>
<columnProperties_item>
<$key>case_restriction</$key>
<$value></$value>
</columnProperties_item>
<columnProperties_item>
<$key>validate_type</$key>
<$value></$value>
</columnProperties_item>
<columnProperties_item>
<$key>length</$key>
<$value>22</$value>
</columnProperties_item>
<columnProperties_item>
<$key>i18n</$key>
<$value></$value>
</columnProperties_item>
<columnProperties_item>
<$key>html_type</$key>
<$value>text</$value>
</columnProperties_item>
<columnProperties_item>
<$key>label</$key>
<$value>fen_seq</$value>
</columnProperties_item>
<columnProperties_item>
<$key>format</$key>
<$value></$value>
</columnProperties_item>
<columnProperties_item>
<$key>type</$key>
<$value>java.lang.Integer</$value>
</columnProperties_item>
<columnProperties_item>
<$key>size</$key>
<$value>22</$value>
</columnProperties_item>
</columnProperties>
</columns_item>
<columns_item>
<class>com.egen.develop.integration.model.VObjectColumn</class>
<discard>false</discard>
<columnName>ies_codigo</columnName>
<columnProperties>
<columnProperties_item>
<$key>not_null</$key>
<$value></$value>
</columnProperties_item>
<columnProperties_item>
<$key>help</$key>
<$value></$value>
</columnProperties_item>
<columnProperties_item>
<$key>case_restriction</$key>
<$value></$value>
</columnProperties_item>
<columnProperties_item>
<$key>validate_type</$key>
<$value></$value>
</columnProperties_item>
<columnProperties_item>
<$key>length</$key>
<$value>22</$value>
</columnProperties_item>
<columnProperties_item>
<$key>i18n</$key>
<$value></$value>
</columnProperties_item>
<columnProperties_item>
<$key>html_type</$key>
<$value>text</$value>
</columnProperties_item>
<columnProperties_item>
<$key>label</$key>
<$value>ies_codigo</$value>
</columnProperties_item>
<columnProperties_item>
<$key>format</$key>
<$value></$value>
</columnProperties_item>
<columnProperties_item>
<$key>type</$key>
<$value>java.lang.Long</$value>
</columnProperties_item>
<columnProperties_item>
<$key>size</$key>
<$value>22</$value>
</columnProperties_item>
</columnProperties>
</columns_item>
<columns_item>
<class>com.egen.develop.integration.model.VObjectColumn</class>
<discard>false</discard>
<columnName>cor_cdgo</columnName>
<columnProperties>
<columnProperties_item>
<$key>not_null</$key>
<$value></$value>
</columnProperties_item>
<columnProperties_item>
<$key>case_restriction</$key>
<$value></$value>
</columnProperties_item>
<columnProperties_item>
<$key>help</$key>
<$value></$value>
</columnProperties_item>
<columnProperties_item>
<$key>validate_type</$key>
<$value></$value>
</columnProperties_item>
<columnProperties_item>
<$key>length</$key>
<$value>22</$value>
</columnProperties_item>
<columnProperties_item>
<$key>html_type</$key>
<$value>text</$value>
</columnProperties_item>
<columnProperties_item>
<$key>i18n</$key>
<$value></$value>
</columnProperties_item>
<columnProperties_item>
<$key>label</$key>
<$value>cor_cdgo</$value>
</columnProperties_item>
<columnProperties_item>
<$key>format</$key>
<$value></$value>
</columnProperties_item>
<columnProperties_item>
<$key>type</$key>
<$value>java.lang.Integer</$value>
</columnProperties_item>
<columnProperties_item>
<$key>size</$key>
<$value>22</$value>
</columnProperties_item>
</columnProperties>
</columns_item>
<columns_item>
<class>com.egen.develop.integration.model.VObjectColumn</class>
<discard>false</discard>
<columnName>tai_codigo</columnName>
<columnProperties>
<columnProperties_item>
<$key>not_null</$key>
<$value></$value>
</columnProperties_item>
<columnProperties_item>
<$key>help</$key>
<$value></$value>
</columnProperties_item>
<columnProperties_item>
<$key>case_restriction</$key>
<$value></$value>
</columnProperties_item>
<columnProperties_item>
<$key>validate_type</$key>
<$value></$value>
</columnProperties_item>
<columnProperties_item>
<$key>length</$key>
<$value>5</$value>
</columnProperties_item>
<columnProperties_item>
<$key>i18n</$key>
<$value></$value>
</columnProperties_item>
<columnProperties_item>
<$key>html_type</$key>
<$value>text</$value>
</columnProperties_item>
<columnProperties_item>
<$key>label</$key>
<$value>tai_codigo</$value>
</columnProperties_item>
<columnProperties_item>
<$key>format</$key>
<$value></$value>
</columnProperties_item>
<columnProperties_item>
<$key>type</$key>
<$value>java.lang.String</$value>
</columnProperties_item>
<columnProperties_item>
<$key>size</$key>
<$value>5</$value>
</columnProperties_item>
</columnProperties>
</columns_item>
<columns_item>
<class>com.egen.develop.integration.model.VObjectColumn</class>
<discard>false</discard>
<columnName>cod_min_fabr</columnName>
<columnProperties>
<columnProperties_item>
<$key>not_null</$key>
<$value></$value>
</columnProperties_item>
<columnProperties_item>
<$key>case_restriction</$key>
<$value></$value>
</columnProperties_item>
<columnProperties_item>
<$key>help</$key>
<$value></$value>
</columnProperties_item>
<columnProperties_item>
<$key>validate_type</$key>
<$value></$value>
</columnProperties_item>
<columnProperties_item>
<$key>length</$key>
<$value>22</$value>
</columnProperties_item>
<columnProperties_item>
<$key>html_type</$key>
<$value>text</$value>
</columnProperties_item>
<columnProperties_item>
<$key>i18n</$key>
<$value></$value>
</columnProperties_item>
<columnProperties_item>
<$key>label</$key>
<$value>cod_min_fabr</$value>
</columnProperties_item>
<columnProperties_item>
<$key>format</$key>
<$value></$value>
</columnProperties_item>
<columnProperties_item>
<$key>type</$key>
<$value>java.lang.Integer</$value>
</columnProperties_item>
<columnProperties_item>
<$key>size</$key>
<$value>22</$value>
</columnProperties_item>
</columnProperties>
</columns_item>
<columns_item>
<class>com.egen.develop.integration.model.VObjectColumn</class>
<discard>false</discard>
<columnName>quantidade_transito</columnName>
<columnProperties>
<columnProperties_item>
<$key>not_null</$key>
<$value></$value>
</columnProperties_item>
<columnProperties_item>
<$key>help</$key>
<$value></$value>
</columnProperties_item>
<columnProperties_item>
<$key>case_restriction</$key>
<$value></$value>
</columnProperties_item>
<columnProperties_item>
<$key>validate_type</$key>
<$value></$value>
</columnProperties_item>
<columnProperties_item>
<$key>length</$key>
<$value>27</$value>
</columnProperties_item>
<columnProperties_item>
<$key>i18n</$key>
<$value></$value>
</columnProperties_item>
<columnProperties_item>
<$key>html_type</$key>
<$value>text</$value>
</columnProperties_item>
<columnProperties_item>
<$key>label</$key>
<$value>quantidade_transito</$value>
</columnProperties_item>
<columnProperties_item>
<$key>format</$key>
<$value></$value>
</columnProperties_item>
<columnProperties_item>
<$key>type</$key>
<$value>java.lang.Double</$value>
</columnProperties_item>
<columnProperties_item>
<$key>size</$key>
<$value>22</$value>
</columnProperties_item>
</columnProperties>
</columns_item>
<columns_item>
<class>com.egen.develop.integration.model.VObjectColumn</class>
<discard>false</discard>
<columnName>quantidade_produzida</columnName>
<columnProperties>
<columnProperties_item>
<$key>not_null</$key>
<$value></$value>
</columnProperties_item>
<columnProperties_item>
<$key>help</$key>
<$value></$value>
</columnProperties_item>
<columnProperties_item>
<$key>case_restriction</$key>
<$value></$value>
</columnProperties_item>
<columnProperties_item>
<$key>validate_type</$key>
<$value></$value>
</columnProperties_item>
<columnProperties_item>
<$key>length</$key>
<$value>27</$value>
</columnProperties_item>
<columnProperties_item>
<$key>html_type</$key>
<$value>text</$value>
</columnProperties_item>
<columnProperties_item>
<$key>i18n</$key>
<$value></$value>
</columnProperties_item>
<columnProperties_item>
<$key>label</$key>
<$value>quantidade_produzida</$value>
</columnProperties_item>
<columnProperties_item>
<$key>format</$key>
<$value></$value>
</columnProperties_item>
<columnProperties_item>
<$key>type</$key>
<$value>java.lang.Double</$value>
</columnProperties_item>
<columnProperties_item>
<$key>size</$key>
<$value>22</$value>
</columnProperties_item>
</columnProperties>
</columns_item>
<columns_item>
<class>com.egen.develop.integration.model.VObjectColumn</class>
<discard>false</discard>
<columnName>quantidade_atraso</columnName>
<columnProperties>
<columnProperties_item>
<$key>not_null</$key>
<$value></$value>
</columnProperties_item>
<columnProperties_item>
<$key>help</$key>
<$value></$value>
</columnProperties_item>
<columnProperties_item>
<$key>case_restriction</$key>
<$value></$value>
</columnProperties_item>
<columnProperties_item>
<$key>validate_type</$key>
<$value></$value>
</columnProperties_item>
<columnProperties_item>
<$key>length</$key>
<$value>27</$value>
</columnProperties_item>
<columnProperties_item>
<$key>i18n</$key>
<$value></$value>
</columnProperties_item>
<columnProperties_item>
<$key>html_type</$key>
<$value>text</$value>
</columnProperties_item>
<columnProperties_item>
<$key>label</$key>
<$value>quantidade_atraso</$value>
</columnProperties_item>
<columnProperties_item>
<$key>format</$key>
<$value></$value>
</columnProperties_item>
<columnProperties_item>
<$key>type</$key>
<$value>java.lang.Double</$value>
</columnProperties_item>
<columnProperties_item>
<$key>size</$key>
<$value>22</$value>
</columnProperties_item>
</columnProperties>
</columns_item>
<columns_item>
<class>com.egen.develop.integration.model.VObjectColumn</class>
<discard>false</discard>
<columnName>data_entrega</columnName>
<columnProperties>
<columnProperties_item>
<$key>not_null</$key>
<$value></$value>
</columnProperties_item>
<columnProperties_item>
<$key>help</$key>
<$value></$value>
</columnProperties_item>
<columnProperties_item>
<$key>case_restriction</$key>
<$value></$value>
</columnProperties_item>
<columnProperties_item>
<$key>validate_type</$key>
<$value></$value>
</columnProperties_item>
<columnProperties_item>
<$key>length</$key>
<$value>22</$value>
</columnProperties_item>
<columnProperties_item>
<$key>html_type</$key>
<$value>text</$value>
</columnProperties_item>
<columnProperties_item>
<$key>i18n</$key>
<$value></$value>
</columnProperties_item>
<columnProperties_item>
<$key>label</$key>
<$value>data_entrega</$value>
</columnProperties_item>
<columnProperties_item>
<$key>format</$key>
<$value></$value>
</columnProperties_item>
<columnProperties_item>
<$key>type</$key>
<$value>java.sql.Date</$value>
</columnProperties_item>
<columnProperties_item>
<$key>size</$key>
<$value>22</$value>
</columnProperties_item>
</columnProperties>
</columns_item>
<columns_item>
<class>com.egen.develop.integration.model.VObjectColumn</class>
<discard>false</discard>
<columnName>data_atualizacao</columnName>
<columnProperties>
<columnProperties_item>
<$key>not_null</$key>
<$value></$value>
</columnProperties_item>
<columnProperties_item>
<$key>help</$key>
<$value></$value>
</columnProperties_item>
<columnProperties_item>
<$key>case_restriction</$key>
<$value></$value>
</columnProperties_item>
<columnProperties_item>
<$key>validate_type</$key>
<$value></$value>
</columnProperties_item>
<columnProperties_item>
<$key>length</$key>
<$value>22</$value>
</columnProperties_item>
<columnProperties_item>
<$key>html_type</$key>
<$value>text</$value>
</columnProperties_item>
<columnProperties_item>
<$key>i18n</$key>
<$value></$value>
</columnProperties_item>
<columnProperties_item>
<$key>label</$key>
<$value>data_atualizacao</$value>
</columnProperties_item>
<columnProperties_item>
<$key>format</$key>
<$value></$value>
</columnProperties_item>
<columnProperties_item>
<$key>type</$key>
<$value>java.sql.Timestamp</$value>
</columnProperties_item>
<columnProperties_item>
<$key>size</$key>
<$value>22</$value>
</columnProperties_item>
</columnProperties>
</columns_item>
<columns_item>
<class>com.egen.develop.integration.model.VObjectColumn</class>
<discard>false</discard>
<columnName>id</columnName>
<columnProperties>
<columnProperties_item>
<$key>not_null</$key>
<$value></$value>
</columnProperties_item>
<columnProperties_item>
<$key>help</$key>
<$value></$value>
</columnProperties_item>
<columnProperties_item>
<$key>case_restriction</$key>
<$value></$value>
</columnProperties_item>
<columnProperties_item>
<$key>validate_type</$key>
<$value></$value>
</columnProperties_item>
<columnProperties_item>
<$key>length</$key>
<$value>22</$value>
</columnProperties_item>
<columnProperties_item>
<$key>i18n</$key>
<$value></$value>
</columnProperties_item>
<columnProperties_item>
<$key>html_type</$key>
<$value>text</$value>
</columnProperties_item>
<columnProperties_item>
<$key>label</$key>
<$value>id</$value>
</columnProperties_item>
<columnProperties_item>
<$key>format</$key>
<$value></$value>
</columnProperties_item>
<columnProperties_item>
<$key>type</$key>
<$value>java.lang.Integer</$value>
</columnProperties_item>
<columnProperties_item>
<$key>size</$key>
<$value>22</$value>
</columnProperties_item>
</columnProperties>
</columns_item>
</columns>
<properties>
<properties_item>
<$key>schema</$key>
<$value></$value>
</properties_item>
<properties_item>
<$key>db_type</$key>
<$value>javaview</$value>
</properties_item>
<properties_item>
<$key>query</$key>
<$value>SELECT 
        r.for_codigo fornecedor_codigo
       ,r.fen_seq      
       ,r.ies_codigo
       ,r.cor_cdgo
       ,r.tai_codigo
       ,r.cod_min_fabr
       ,r.quantidade_transito
       ,r.quantidade_produzida
       ,r.quantidade_atraso
       ,r.data_entrega
	   ,r.data_atualizacao
	   ,r.id
   FROM req_sdo_abastecimento_fornec r
  WHERE data_atualizacao = (SELECT MAX(data_atualizacao)
                              FROM req_sdo_abastecimento_fornec
                             WHERE ies_codigo = r.ies_codigo
                               AND cor_cdgo = r.cor_cdgo
                               AND tai_codigo = r.tai_codigo
                               AND cod_min_fabr = r.cod_min_fabr
                               AND for_codigo = r.for_codigo
                               AND fen_seq = r.fen_seq
							   and id = r.id)
 </$value>
</properties_item>
<properties_item>
<$key>metadata</$key>
<$value></$value>
</properties_item>
</properties>
